README.md
setup.py
async_process_pool/__init__.py
async_process_pool/__version__.py
async_process_pool/async_process_queue.py
async_process_pool/process_pool.py
async_process_pool/watchdog.py
async_process_pool.egg-info/PKG-INFO
async_process_pool.egg-info/SOURCES.txt
async_process_pool.egg-info/dependency_links.txt
async_process_pool.egg-info/top_level.txt