Metadata-Version: 2.1
Name: async-process-pool
Version: 0.0.2
Summary: Async Process Pool and Queue
Home-page: https://github.com/hutomadotAI/async-process-pool
Author: Paul Annetts
Author-email: paul@hutoma.ai
License: UNKNOWN
Platform: UNKNOWN
Classifier: Development Status :: 4 - Beta
Classifier: Framework :: AsyncIO
Classifier: License :: OSI Approved :: Apache Software License
Classifier: Programming Language :: Python :: 3 :: Only
Classifier: Programming Language :: Python :: 3.7
Classifier: Operating System :: OS Independent
